futu_stock_mcp_server/__init__.py
futu_stock_mcp_server/server.py
futu_stock_mcp_server-0.1.9.dist-info/METADATA
futu_stock_mcp_server-0.1.9.dist-info/WHEEL
futu_stock_mcp_server-0.1.9.dist-info/entry_points.txt
futu_stock_mcp_server-0.1.9.dist-info/licenses/LICENSE
futu_stock_mcp_server-0.1.9.dist-info/RECORD
