Metadata-Version: 2.4
Name: futu-stock-mcp-server
Version: 0.1.9
Summary: A Model Context Protocol (MCP) server for accessing Futu OpenAPI functionality
Project-URL: Homepage, https://github.com/shuizhengqi1/futu-stock-mcp-server
Project-URL: Documentation, https://github.com/shuizhengqi1/futu-stock-mcp-server#readme
Project-URL: Repository, https://github.com/shuizhengqi1/futu-stock-mcp-server
Project-URL: Issues, https://github.com/shuizhengqi1/futu-stock-mcp-server/issues
Author-email: shuizhengqi <shuizhengqi1@163.com>
Maintainer-email: shuizhengqi <shuizhengqi1@163.com>
License: MIT
License-File: LICENSE
Keywords: api,finance,futu,mcp,stock,trading
Classifier: Development Status :: 3 - Alpha
Classifier: Intended Audience :: Developers
Classifier: Intended Audience :: Financial and Insurance Industry
Classifier: License :: OSI Approved :: MIT License
Classifier: Programming Language :: Python :: 3
Classifier: Programming Language :: Python :: 3.10
Classifier: Programming Language :: Python :: 3.11
Classifier: Programming Language :: Python :: 3.12
Classifier: Topic :: Office/Business :: Financial
Classifier: Topic :: Software Development :: Libraries :: Python Modules
Requires-Python: >=3.10
Requires-Dist: aiohttp
Requires-Dist: fastapi
Requires-Dist: futu-api
Requires-Dist: loguru
Requires-Dist: mcp[cli]>=1.6.0
Requires-Dist: psutil
Requires-Dist: pydantic
Requires-Dist: python-dotenv
Requires-Dist: uvicorn
Requires-Dist: websockets
Provides-Extra: dev
Requires-Dist: black; extra == 'dev'
Requires-Dist: mypy; extra == 'dev'
Requires-Dist: pytest; extra == 'dev'
Requires-Dist: pytest-asyncio; extra == 'dev'
Requires-Dist: ruff; extra == 'dev'
